ecstasy/__init__.py
ecstasy/errors.py
ecstasy/flags.py
ecstasy/parser.py
ecstasy-0.1.3.dist-info/DESCRIPTION.rst
ecstasy-0.1.3.dist-info/METADATA
ecstasy-0.1.3.dist-info/metadata.json
ecstasy-0.1.3.dist-info/RECORD
ecstasy-0.1.3.dist-info/top_level.txt
ecstasy-0.1.3.dist-info/WHEEL
test/__init__.py
test/test_errors.py
test/test_flags.py
test/test_parser.py
