Metadata-Version: 1.1
Name: ecstasy
Version: 0.1.3
Summary: A command-line-tool beautifier.
Home-page: https://github.com/goldsborough/ecstasy
Author: Peter Goldsborough
Author-email: petergoldsborough@hotmail.com
License: MIT
Keywords: command-line tools formatting styling beautifier markup
Platform: UNKNOWN
Classifier: Development Status :: 4 - Beta
Classifier: Intended Audience :: Developers
Classifier: Topic :: Software Development
Classifier: License :: OSI Approved :: MIT License
Classifier: Programming Language :: Python
Classifier: Programming Language :: Python :: 2
Classifier: Programming Language :: Python :: 2.6
Classifier: Programming Language :: Python :: 2.7
Classifier: Programming Language :: Python :: 3
Classifier: Programming Language :: Python :: 3.2
Classifier: Programming Language :: Python :: 3.3
Classifier: Programming Language :: Python :: 3.4
